<?xml version="1.0" encoding="UTF-8"?>

<lansuite>
	<header>
		<filetype>LanSuite</filetype>
		<version>2.0</version>
		<source>http://www.lansuite.de</source>
		<date>2009-12-30 11:44</date>
	</header>
	<table>
		<table_head>
			<name>translation</name>
		</table_head>
		<content>
			<entry>
				<id>0b32fe0308d9689169d8f7038bbd1cf0</id>
				<org>Bitte geben Sie einen Namen ein</org>
				<file>sponsor</file>
			</entry>
			<entry>
				<id>c9bcac873e61cef1c12bae8463c38266</id>
				<org>Der Text darf nicht mehr als 5000 Zeichen enthalten</org>
				<file>sponsor</file>
			</entry>
			<entry>
				<id>49ee3087348e8d44e1feda1917443987</id>
				<org>Name</org>
				<file>sponsor</file>
			</entry>
			<entry>
				<id>88de6e5fc8227d345e6d0a62e0335079</id>
				<org>Ziel-URL</org>
				<file>sponsor</file>
			</entry>
			<entry>
				<id>f855e026f8fb97530d061cbe33a9e23b</id>
				<org>Auf Sponsorenseite</org>
				<file>sponsor</file>
			</entry>
			<entry>
				<id>c1afe6a9e4be7a3a6c30db1049a9d44a</id>
				<org>Der Banner wird auf der Sponsorenseite angezeigt</org>
				<file>sponsor</file>
			</entry>
			<entry>
				<id>6e714e80acd43626e7a7be03395a3c14</id>
				<org>Bild-Upload</org>
				<file>sponsor</file>
			</entry>
			<entry>
				<id>54047e58697538f843cfbb3cb5002269</id>
				<org>Oder: Bild-URL</org>
				<file>sponsor</file>
			</entry>
			<entry>
				<id>1cb8a46bc5cdfc78b3160d12eb7e8215</id>
				<org>Oder: Bild-Code (z.B. Flash)</org>
				<file>sponsor</file>
			</entry>
			<entry>
				<id>62e835bfc6b3600a4abd331cdf9aa22c</id>
				<org>Wenn Sie hier keine Datei angeben, wird der Banner/Button automatisch durch verkleinern der oben angegebenen Datei erzeugt (Funktioniert nur bei heraufgeladenen Dateien).</org>
				<file>sponsor</file>
			</entry>
			<entry>
				<id>25f410e7fce2d9cb781f4856446a59e0</id>
				<org>In Rotations-Banner</org>
				<file>sponsor</file>
			</entry>
			<entry>
				<id>0849402f03de3ede65ea01d16dbc5572</id>
				<org>Der Banner wird oben in den Rotations-Banner aufgenommen</org>
				<file>sponsor</file>
			</entry>
			<entry>
				<id>d854e6e2fbd0c25ef3f7f7f621d82fc6</id>
				<org>In Sponsoren-Box</org>
				<file>sponsor</file>
			</entry>
			<entry>
				<id>dea6029483312ce02fc50247b130472b</id>
				<org>Der Banner wird in der Sponsoren-Box angezeigt</org>
				<file>sponsor</file>
			</entry>
			<entry>
				<id>1b26a8bba6e841f1c375b283db5c1c61</id>
				<org>Keine</org>
				<file>sponsor</file>
			</entry>
			<entry>
				<id>2eef4c730b9ca0a3ce916ac3f5121a49</id>
				<org>Sponsor einem Turnier zuordnen</org>
				<file>sponsor</file>
			</entry>
			<entry>
				<id>52f5e0bc3859bc5f5e25130b6c7e8881</id>
				<org>Position</org>
				<file>sponsor</file>
			</entry>
			<entry>
				<id>9dffbf69ffba8bc38bc4e01abf4b1675</id>
				<org>Text</org>
				<file>sponsor</file>
			</entry>
			<entry>
				<id>e90c90901180d6fe57d8931fc7496439</id>
				<org>Diese Banner-ID existiert nicht! Manipulationsversuch oder Datenbankfehler. Bitte ZURÜCK anklicken.</org>
				<file>sponsor</file>
			</entry>
			<entry>
				<id>85b8dc97a3238cf702a94a4a7798d1b8</id>
				<org>Wollen Sie den Sponsor &lt;b&gt;%1&lt;/b&gt; wirklich löschen?</org>
				<file>sponsor</file>
			</entry>
			<entry>
				<id>db4f7225146afee4c3853dd032b9713b</id>
				<org>Der Sponsor &lt;b&gt;%1&lt;/b&gt; wurde erfolgreich gelöscht</org>
				<file>sponsor</file>
			</entry>
			<entry>
				<id>b61909ddc1b013586edbe2ef7cee8aa8</id>
				<org>Unsere Sponsoren</org>
				<file>sponsor</file>
			</entry>
			<entry>
				<id>7635b2a31429226003f306ba6a8a58e4</id>
				<org>Bei den folgenden Sponsoren möchten wir uns herzlich für ihren Beitrag zu unserer Veranstaltung bedanken.</org>
				<file>sponsor</file>
			</entry>
			<entry>
				<id>1a2ef910cbe884f204d34cea2f6cb453</id>
				<org>Sie werden weitergeleitet...</org>
				<file>sponsor</file>
			</entry>
			<entry>
				<id>715380d7bcc0b403482990fa332214cc</id>
				<org>Statistiken</org>
				<file>sponsor</file>
			</entry>
			<entry>
				<id>e3839fbca64cc7dd77177d5f4ae0584e</id>
				<org>Hier sehen Sie die Statistiken zu den einzelnen Sponsoren der Sponsorliste</org>
				<file>sponsor</file>
			</entry>
			<entry>
				<id>4c6f7027a4cbad5046b9784421421f6b</id>
				<org>Angezeigt</org>
				<file>sponsor</file>
			</entry>
			<entry>
				<id>95914c75dd59d52a35912b186df37ec3</id>
				<org>Angeklickt</org>
				<file>sponsor</file>
			</entry>
			<entry>
				<id>fa7bba8ae56844137aa694ed0630e971</id>
				<org>Klickrate</org>
				<file>sponsor</file>
			</entry>
			<entry>
				<id>a9fb96c1ae5d25a84580c4b7c987143d</id>
				<org>Wir danken</org>
				<file>sponsor</file>
			</entry>
		</content>
	</table>
</lansuite>
